aztk/__init__.py
aztk/error.py
aztk/version.py
aztk/client/__init__.py
aztk/client/client.py
aztk/client/base/__init__.py
aztk/client/base/base_operations.py
aztk/client/base/helpers/__init__.py
aztk/client/base/helpers/create_user_on_cluster.py
aztk/client/base/helpers/create_user_on_node.py
aztk/client/base/helpers/delete_user_on_cluster.py
aztk/client/base/helpers/delete_user_on_node.py
aztk/client/base/helpers/generate_user_on_cluster.py
aztk/client/base/helpers/generate_user_on_node.py
aztk/client/base/helpers/get_application_log.py
aztk/client/base/helpers/get_recent_job.py
aztk/client/base/helpers/get_remote_login_settings.py
aztk/client/base/helpers/get_task_state.py
aztk/client/base/helpers/list_tasks.py
aztk/client/base/helpers/node_run.py
aztk/client/base/helpers/run.py
aztk/client/base/helpers/ssh_into_node.py
aztk/client/base/helpers/task_table.py
aztk/client/cluster/__init__.py
aztk/client/cluster/operations.py
aztk/client/cluster/helpers/__init__.py
aztk/client/cluster/helpers/copy.py
aztk/client/cluster/helpers/create.py
aztk/client/cluster/helpers/delete.py
aztk/client/cluster/helpers/get.py
aztk/client/cluster/helpers/list.py
aztk/client/cluster/helpers/wait_for_task_to_complete.py
aztk/client/job/__init__.py
aztk/client/job/operations.py
aztk/client/job/helpers/__init__.py
aztk/client/job/helpers/submit.py
aztk/core/__init__.py
aztk/core/models/__init__.py
aztk/core/models/fields.py
aztk/core/models/model.py
aztk/core/models/validators.py
aztk/internal/__init__.py
aztk/internal/configuration_base.py
aztk/internal/docker_cmd.py
aztk/internal/cluster_data/__init__.py
aztk/internal/cluster_data/blob_data.py
aztk/internal/cluster_data/cluster_data.py
aztk/internal/cluster_data/node_data.py
aztk/models/__init__.py
aztk/models/application_log.py
aztk/models/cluster.py
aztk/models/cluster_configuration.py
aztk/models/cluster_state.py
aztk/models/file.py
aztk/models/file_share.py
aztk/models/node_output.py
aztk/models/port_forward_specification.py
aztk-0.10.3.dist-info/LICENSE
aztk-0.10.3.dist-info/METADATA
aztk-0.10.3.dist-info/WHEEL
aztk-0.10.3.dist-info/entry_points.txt
aztk-0.10.3.dist-info/top_level.txt
aztk-0.10.3.dist-info/RECORD
