Metadata-Version: 2.1
Name: aztk
Version: 0.10.3
Summary: On-demand, Dockerized, Spark Jobs on Azure (powered by Azure Batch)
Home-page: https://github.com/Azure/aztk
Author: Microsoft
Author-email: askaztk@microsoft.com
License: MIT
Project-URL: Documentation, https://github.com/Azure/aztk/wiki/
Project-URL: Source, https://github.com/Azure/aztk/
Project-URL: Tracker, https://github.com/Azure/aztk/issues
Platform: UNKNOWN
Classifier: Development Status :: 4 - Beta
Classifier: Intended Audience :: Developers
Classifier: License :: OSI Approved :: MIT License
Classifier: Programming Language :: Python :: 3.5
Classifier: Programming Language :: Python :: 3.6
Requires-Python: >=3.5
Requires-Dist: azure-batch (~=5.1.0)
Requires-Dist: azure-mgmt-batch (~=5.0.1)
Requires-Dist: azure-mgmt-storage (~=3.0.0)
Requires-Dist: azure-storage-blob (~=1.3.1)
Requires-Dist: azure-cosmosdb-table (~=1.0.5)
Requires-Dist: pycryptodomex (~=3.6.6)
Requires-Dist: PyYAML (~=3.13)
Requires-Dist: paramiko (~=2.4.2)
